odoo/addons/account_statement_import_fr_cfonb/README.rst
odoo/addons/account_statement_import_fr_cfonb/__init__.py
odoo/addons/account_statement_import_fr_cfonb/__manifest__.py
odoo/addons/account_statement_import_fr_cfonb/i18n/account_bank_statement_import_fr_cfonb.pot
odoo/addons/account_statement_import_fr_cfonb/i18n/account_statement_import_fr_cfonb.pot
odoo/addons/account_statement_import_fr_cfonb/i18n/nb_NO.po
odoo/addons/account_statement_import_fr_cfonb/models/__init__.py
odoo/addons/account_statement_import_fr_cfonb/models/account_journal.py
odoo/addons/account_statement_import_fr_cfonb/readme/CONTRIBUTORS.rst
odoo/addons/account_statement_import_fr_cfonb/readme/DESCRIPTION.rst
odoo/addons/account_statement_import_fr_cfonb/readme/USAGE.rst
odoo/addons/account_statement_import_fr_cfonb/static/description/icon.png
odoo/addons/account_statement_import_fr_cfonb/static/description/index.html
odoo/addons/account_statement_import_fr_cfonb/views/account_statement_import.xml
odoo/addons/account_statement_import_fr_cfonb/wizard/__init__.py
odoo/addons/account_statement_import_fr_cfonb/wizard/account_statement_import.py
odoo14_addon_account_statement_import_fr_cfonb-14.0.1.1.0.dist-info/METADATA
odoo14_addon_account_statement_import_fr_cfonb-14.0.1.1.0.dist-info/WHEEL
odoo14_addon_account_statement_import_fr_cfonb-14.0.1.1.0.dist-info/top_level.txt
odoo14_addon_account_statement_import_fr_cfonb-14.0.1.1.0.dist-info/RECORD
